cheatos/__init__.py
cheatos/cli.py
cheatos/commands.py
cheatos/completers.py
cheatos/io.py
cheatos/utils.py
cheatos-1.0.2.dist-info/METADATA
cheatos-1.0.2.dist-info/WHEEL
cheatos-1.0.2.dist-info/entry_points.txt
cheatos-1.0.2.dist-info/licenses/LICENSE
cheatos-1.0.2.dist-info/RECORD
