Metadata-Version: 2.4
Name: cheatos
Version: 1.0.2
Summary: Cheatos: Your terminal post-it notes manager
Project-URL: Homepage, https://github.com/Gorbiel/Cheatos?tab=readme-ov-file#cheatos
Project-URL: Documentation, https://github.com/Gorbiel/Cheatos/wiki
Project-URL: Issues, https://github.com/Gorbiel/Cheatos/issues
Project-URL: Source, https://github.com/Gorbiel/Cheatos
Author-email: Gorbiel <tba@example.com>
License: MIT
License-File: LICENSE
Keywords: cheatsheet,cli,notes,productivity,terminal
Classifier: Development Status :: 5 - Production/Stable
Classifier: Environment :: Console
Classifier: Intended Audience :: Developers
Classifier: License :: OSI Approved :: MIT License
Classifier: Operating System :: OS Independent
Classifier: Programming Language :: Python :: 3
Classifier: Programming Language :: Python :: 3.7
Classifier: Programming Language :: Python :: 3.10
Classifier: Topic :: Utilities
Requires-Python: >=3.7
Requires-Dist: appdirs
Requires-Dist: argcomplete
Requires-Dist: pymongo
Requires-Dist: tomli
